easy_mcp/__init__.py
easy_mcp/bridge.py
easy_mcp/client.py
easy_mcp/streaming.py
easy_mcp_langchain-0.1.2.dist-info/licenses/LICENSE
easy_mcp_langchain-0.1.2.dist-info/METADATA
easy_mcp_langchain-0.1.2.dist-info/WHEEL
easy_mcp_langchain-0.1.2.dist-info/top_level.txt
easy_mcp_langchain-0.1.2.dist-info/RECORD
