Metadata-Version: 2.4
Name: easy-mcp-langchain
Version: 0.1.2
Summary: Seamlessly connect MCP tools to LangChain Agents.
Home-page: https://github.com/Annyfee/easy-mcp
Author: 
Author-email: 2287551746@qq.com
License: MIT License
Classifier: Development Status :: 3 - Alpha
Classifier: Intended Audience :: Developers
Classifier: License :: OSI Approved :: MIT License
Classifier: Programming Language :: Python :: 3
Classifier: Programming Language :: Python :: 3.8
Classifier: Programming Language :: Python :: 3.9
Classifier: Programming Language :: Python :: 3.10
Classifier: Programming Language :: Python :: 3.11
Classifier: Topic :: Software Development :: Libraries :: Python Modules
Requires-Python: >=3.8
License-File: LICENSE
Requires-Dist: langchain-core
Requires-Dist: pydantic
Requires-Dist: mcp
Requires-Dist: python-dotenv
Dynamic: author-email
Dynamic: home-page
Dynamic: license-file
Dynamic: requires-python
